docs/post_process_html.py
docs/source/conf.py
examples/analytic_example/Albanian.tree.152tax.nwk
examples/analytic_example/Anolis.tre
examples/analytic_example/demo2.tree
examples/analytic_example/demo2_ls.tsv
examples/analytic_example/demo_acr_ls.sh
examples/analytic_example/metadata_tab.csv
examples/analytic_example/metadata_tab_ls.csv
examples/analytic_example/show_tree_props.py
examples/analytic_example/svl.csv
examples/automatic_query/basic_example1.nw
examples/automatic_query/basic_example1_metadata1.tsv
examples/automatic_query/collapse_demo.sh
examples/automatic_query/color.config.collapsed
examples/automatic_query/color.config.query
examples/automatic_query/color.config.template
examples/automatic_query/highlight_demo.sh
examples/automatic_query/prune_demo.sh
examples/basic_example0/boolean.tsv
examples/basic_example0/categorical.tsv
examples/basic_example0/categorical_ancestor.tsv
examples/basic_example0/categorical_duplicated.tsv
examples/basic_example0/data.array
examples/basic_example0/demo1.tree
examples/basic_example0/numerical.tsv
examples/basic_example0/run_demo.sh
examples/basic_example0/show_tree_props.py
examples/basic_example0/show_tree_props_ancestor.py
examples/basic_example1/basic_example1.nw
examples/basic_example1/basic_example1_metadata.tsv
examples/basic_example1/basic_example1_metadata1.tsv
examples/basic_example1/basic_example1_metadata2.tsv
examples/basic_example1/example1_demo.sh
examples/basic_example2/FluA_H3_AA.fas
examples/basic_example2/MCC_FluA_H3.nw
examples/basic_example2/MCC_FluA_H3_Genotype.txt
examples/basic_example2/diauxic.array
examples/basic_example2/diauxic.nw
examples/basic_example2/example2_demo.sh
examples/custom_color/basic_example1.nw
examples/custom_color/basic_example1_metadata1.tsv
examples/custom_color/basic_example1_metadata2.tsv
examples/custom_color/color.boolean.config
examples/custom_color/color.categorical.config
examples/custom_color/color.config.template
examples/custom_color/color.datamatrix.config
treeprofiler-2.0.4.dist-info/licenses/LICENSE
treeprofiler-2.0.4.dist-info/METADATA
treeprofiler-2.0.4.dist-info/WHEEL
treeprofiler-2.0.4.dist-info/entry_points.txt
treeprofiler-2.0.4.dist-info/top_level.txt
treeprofiler-2.0.4.dist-info/RECORD
