Metadata-Version: 2.4
Name: treeprofiler
Version: 2.0.4
Summary: A command line tool to annotate and visualize metadata in phylogenetic tree.
Home-page: https://github.com/compgenomicslab/MetaTreeDrawer
Author: Ziqi Deng, Jaime Huerta-Cepas
Author-email: Ziqi Deng <dengziqi1234@gmail.com>, Jaime Huerta-Cepas <jhcepas@gmail.com>
Maintainer: Ziqi Deng
Maintainer-email: dengziqi1234@gmail.com
License:                     GNU GENERAL PUBLIC LICENSE
Project-URL: Homepage, http://dengzq1234.github.io/TreeProfiler/
Classifier: Programming Language :: Python :: 3
Classifier: License :: OSI Approved :: GNU General Public License v3 or later (GPLv3+)
Classifier: Development Status :: 6 - Mature
Classifier: Environment :: Console
Classifier: Environment :: X11 Applications :: Qt
Classifier: Intended Audience :: Developers
Classifier: Intended Audience :: Other Audience
Classifier: Intended Audience :: Science/Research
Classifier: Natural Language :: English
Classifier: Operating System :: MacOS
Classifier: Operating System :: Microsoft :: Windows
Classifier: Operating System :: POSIX :: Linux
Classifier: Topic :: Scientific/Engineering :: Bio-Informatics
Classifier: Topic :: Scientific/Engineering :: Visualization
Classifier: Topic :: Software Development :: Libraries :: Python Modules
Requires-Python: >=3.10
License-File: LICENSE
Requires-Dist: numpy<2,>=1.25
Requires-Dist: biopython>=1.8
Requires-Dist: selenium>=4.24.0
Requires-Dist: scipy>=1.8.0
Requires-Dist: matplotlib>=3.4.0
Requires-Dist: pymc>=5.0.0
Requires-Dist: pyvirtualdisplay
Requires-Dist: webdriver_manager>=4.0
Dynamic: author
Dynamic: home-page
Dynamic: license-file
Dynamic: maintainer
Dynamic: maintainer-email
